README.md
setup.py
bunnylog/__init__.py
bunnylog.egg-info/PKG-INFO
bunnylog.egg-info/SOURCES.txt
bunnylog.egg-info/dependency_links.txt
bunnylog.egg-info/requires.txt
bunnylog.egg-info/top_level.txt