Metadata-Version: 1.0
Name: bunnylog
Version: 0.2.0
Summary: BunnyCDN log parser
Home-page: https://github.com/gkbrk/bunnylog-py
Author: Gokberk Yaltirakli
Author-email: opensource@gkbrk.com
License: UNKNOWN
Project-URL: Bug Tracker, https://github.com/gkbrk/bunnylog-py/issues
Project-URL: Source Code, https://github.com/gkbrk/bunnylog-py
Keywords: parser cdn log BunnyCDN
Platform: UNKNOWN
